approck_messaging/__init__.py
approck_messaging/models/__init__.py
approck_messaging/models/message.py
approck_messaging/publisher.py
approck_messaging/subscriber.py
approck_messaging-0.1.9.dist-info/METADATA
approck_messaging-0.1.9.dist-info/WHEEL
approck_messaging-0.1.9.dist-info/RECORD
