Metadata-Version: 2.3
Name: approck-messaging
Version: 0.1.9
Summary: 
Author: Aleksey Dalekin
Author-email: ald@approck.pro
Requires-Python: >=3.10,<4.0
Classifier: Programming Language :: Python :: 3
Classifier: Programming Language :: Python :: 3.10
Classifier: Programming Language :: Python :: 3.11
Classifier: Programming Language :: Python :: 3.12
Classifier: Programming Language :: Python :: 3.13
Provides-Extra: transport
Requires-Dist: faststream[redis] (>=0.5.9,<0.6.0) ; extra == "transport"
Requires-Dist: pydantic[dotenv,email] (>=2.7.1,<3.0.0)
